chrome_master/__init__.py
chrome_master/dom_handler.py
chrome_master/handler.py
chrome_master/input_handler.py
chrome_master/log_handler.py
chrome_master/network_handler.py
chrome_master/page_handler.py
chrome_master/remote_debugger.py
chrome_master/runtime_handler.py
chrome_master/target_handler.py
chrome_master/util.py
chrome_master-1.4.0.dist-info/METADATA
chrome_master-1.4.0.dist-info/WHEEL
chrome_master-1.4.0.dist-info/top_level.txt
chrome_master-1.4.0.dist-info/RECORD
